vika/__init__.py
vika/apitable.py
vika/const.py
vika/exceptions.py
vika/request.py
vika/utils.py
vika/datasheet/__init__.py
vika/datasheet/datasheet.py
vika/datasheet/datasheet_manager.py
vika/datasheet/field_manager.py
vika/datasheet/query_set.py
vika/datasheet/record.py
vika/datasheet/record_manager.py
vika/datasheet/view_manager.py
vika/node/__init__.py
vika/node/node_manager.py
vika/space/__init__.py
vika/space/space.py
vika/space/space_manager.py
vika/types/__init__.py
vika/types/embedlink.py
vika/types/field.py
vika/types/node.py
vika/types/record.py
vika/types/response.py
vika/types/space.py
vika/types/unit_model.py
vika/types/view.py
vika/unit/__init__.py
vika/unit/member.py
vika/unit/role.py
vika/unit/team.py
vika/unit/unit.py
vika-1.3.1.dist-info/LICENSE
vika-1.3.1.dist-info/METADATA
vika-1.3.1.dist-info/WHEEL
vika-1.3.1.dist-info/top_level.txt
vika-1.3.1.dist-info/RECORD
