Metadata-Version: 2.1
Name: vika
Version: 1.3.1
Summary: 维格表官方 Python SDK
Home-page: https://github.com/vikadata/vika.py
Author: vikadata
Author-email: dev@vikadata.com
Classifier: Programming Language :: Python :: 3
Classifier: License :: OSI Approved :: MIT License
Classifier: Operating System :: OS Independent
Requires-Python: >=3.6
License-File: LICENSE
Requires-Dist: requests (<=2.31.0)
Requires-Dist: pydantic (==1.7)
Requires-Dist: environs (<=9.5.0)
